{"name":"as user i want to input all valid data in get user information","id":"as-a-user-i-want-to-get-user-information;as-user-i-want-to-input-all-valid-data-in-get-user-information","testSteps":[{"number":1,"description":"Given user have endpoint auth","duration":11462,"startTime":"2023-05-11T18:53:26.904+07:00[Asia/Bangkok]","result":"SUCCESS","precondition":false,"level":0,"children":[{"number":2,"description":"Set endpoint auth","duration":5,"startTime":"2023-05-11T18:53:38.087+07:00[Asia/Bangkok]","result":"SUCCESS","precondition":false,"level":1}]},{"number":3,"description":"When user send endpoint Auth","duration":46465,"startTime":"2023-05-11T18:53:38.375+07:00[Asia/Bangkok]","result":"SUCCESS","precondition":false,"level":0,"children":[{"number":4,"description":"Send enpoint auth","duration":46456,"startTime":"2023-05-11T18:53:38.379+07:00[Asia/Bangkok]","result":"SUCCESS","precondition":false,"level":1,"children":[{"number":5,"description":"Set endpoint auth","duration":1,"startTime":"2023-05-11T18:53:57.490+07:00[Asia/Bangkok]","result":"SUCCESS","precondition":false,"level":2},{"number":6,"description":"POST https://altashop-api.fly.dev/api/auth/login","duration":0,"startTime":"2023-05-11T18:54:17.382+07:00[Asia/Bangkok]","result":"SUCCESS","restQuery":{"method":"POST","path":"https://altashop-api.fly.dev/api/auth/login","content":"{\n    \"password\": \"nisa\",\n    \"email\": \"nisauzz@gmail.com\"\n}","contentType":"application/json","requestHeaders":"Accept\u003d*/*\r\n\t\t\t\tContent-Type\u003dapplication/json","requestCookies":"","responseHeaders":"content-type: application/json\r\ndate: Thu, 11 May 2023 11:54:16 GMT\r\ncontent-encoding: gzip\r\ntransfer-encoding: chunked\r\nserver: Fly/3f2597ca (2023-05-03)\r\nvia: 1.1 fly.io\r\nfly-request-id: 01H05AJVXM38VB9W4ZFZE3Z0TJ-sin\r","responseCookies":"\r","responseBody":"{\n    \"error\": \"record not found\"\n}","statusCode":400},"precondition":false,"level":2}]}]},{"number":7,"description":"When user has endpoint to get user information","duration":15,"startTime":"2023-05-11T18:54:24.845+07:00[Asia/Bangkok]","result":"SUCCESS","precondition":false,"level":0,"children":[{"number":8,"description":"Set endpoint user info","duration":1,"startTime":"2023-05-11T18:54:24.853+07:00[Asia/Bangkok]","result":"SUCCESS","precondition":false,"level":1}]},{"number":9,"description":"And user get user information","duration":767,"startTime":"2023-05-11T18:54:24.863+07:00[Asia/Bangkok]","result":"SUCCESS","precondition":false,"level":0,"children":[{"number":10,"description":"Send enpoint user info","duration":752,"startTime":"2023-05-11T18:54:24.870+07:00[Asia/Bangkok]","result":"SUCCESS","precondition":false,"level":1,"children":[{"number":11,"description":"Set endpoint user info","duration":3,"startTime":"2023-05-11T18:54:24.882+07:00[Asia/Bangkok]","result":"SUCCESS","precondition":false,"level":2},{"number":12,"description":"GET https://altashop-api.fly.dev/api/auth/info","duration":0,"startTime":"2023-05-11T18:54:25.622+07:00[Asia/Bangkok]","result":"SUCCESS","restQuery":{"method":"GET","path":"https://altashop-api.fly.dev/api/auth/info","content":"","contentType":"null","requestHeaders":"Authorization\u003dBearer null\r\n\t\t\t\tAccept\u003d*/*","requestCookies":"","responseHeaders":"content-type: application/json\r\ndate: Thu, 11 May 2023 11:54:24 GMT\r\ncontent-encoding: gzip\r\ntransfer-encoding: chunked\r\nserver: Fly/3f2597ca (2023-05-03)\r\nvia: 1.1 fly.io\r\nfly-request-id: 01H05AK4AD8C533R43X6F71ZVZ-sin\r","responseCookies":"\r","responseBody":"{\n    \"error\": \"token contains an invalid number of segments\"\n}","statusCode":401},"precondition":false,"level":2}]}]},{"number":13,"description":"Then user get user information status code 200","duration":689,"startTime":"2023-05-11T18:54:25.631+07:00[Asia/Bangkok]","precondition":false,"level":0,"children":[{"number":14,"description":"Response code","duration":681,"startTime":"2023-05-11T18:54:25.637+07:00[Asia/Bangkok]","exception":{"errorType":"java.lang.AssertionError","message":"1 expectation failed.\nExpected status code \u003c200\u003e but was \u003c401\u003e.\n","stackTrace":[{"declaringClass":"io.restassured.internal.ResponseSpecificationImpl","methodName":"validateResponseIfRequired","fileName":"ResponseSpecificationImpl.groovy","lineNumber":696},{"declaringClass":"io.restassured.internal.ResponseSpecificationImpl","methodName":"this$2$validateResponseIfRequired","fileName":"ResponseSpecificationImpl.groovy","lineNumber":-1},{"declaringClass":"io.restassured.internal.ResponseSpecificationImpl","methodName":"statusCode","fileName":"ResponseSpecificationImpl.groovy","lineNumber":135},{"declaringClass":"io.restassured.internal.ResponseSpecificationImpl","methodName":"statusCode","fileName":"ResponseSpecificationImpl.groovy","lineNumber":143},{"declaringClass":"io.restassured.internal.ValidatableResponseOptionsImpl","methodName":"statusCode","fileName":"ValidatableResponseOptionsImpl.java","lineNumber":89},{"declaringClass":"starter.pages.UserInfoPage","methodName":"lambda$responseCode$0","fileName":"UserInfoPage.java","lineNumber":49},{"declaringClass":"net.serenitybdd.rest.SerenityRest","methodName":"restAssuredThat","fileName":"SerenityRest.java","lineNumber":626},{"declaringClass":"starter.pages.UserInfoPage","methodName":"responseCode","fileName":"UserInfoPage.java","lineNumber":49},{"declaringClass":"starter.stepdefinitions.UserInfoSteps","methodName":"userGetUserInformationStatusCode","fileName":"UserInfoSteps.java","lineNumber":37},{"declaringClass":"io.cucumber.java.Invoker","methodName":"doInvoke","fileName":"Invoker.java","lineNumber":66},{"declaringClass":"io.cucumber.java.Invoker","methodName":"invoke","fileName":"Invoker.java","lineNumber":24},{"declaringClass":"io.cucumber.java.AbstractGlueDefinition","methodName":"invokeMethod","fileName":"AbstractGlueDefinition.java","lineNumber":47},{"declaringClass":"io.cucumber.java.JavaStepDefinition","methodName":"execute","fileName":"JavaStepDefinition.java","lineNumber":29},{"declaringClass":"io.cucumber.core.runner.CoreStepDefinition","methodName":"execute","fileName":"CoreStepDefinition.java","lineNumber":66},{"declaringClass":"io.cucumber.core.runner.PickleStepDefinitionMatch","methodName":"runStep","fileName":"PickleStepDefinitionMatch.java","lineNumber":63},{"declaringClass":"io.cucumber.core.runner.TestStep","methodName":"executeStep","fileName":"TestStep.java","lineNumber":84},{"declaringClass":"io.cucumber.core.runner.TestStep","methodName":"run","fileName":"TestStep.java","lineNumber":56},{"declaringClass":"io.cucumber.core.runner.PickleStepTestStep","methodName":"run","fileName":"PickleStepTestStep.java","lineNumber":51},{"declaringClass":"io.cucumber.core.runner.TestCase","methodName":"run","fileName":"TestCase.java","lineNumber":84},{"declaringClass":"io.cucumber.core.runner.Runner","methodName":"runPickle","fileName":"Runner.java","lineNumber":75},{"declaringClass":"io.cucumber.core.runtime.CucumberExecutionContext","methodName":"lambda$runTestCase$5","fileName":"CucumberExecutionContext.java","lineNumber":130},{"declaringClass":"io.cucumber.core.runtime.RethrowingThrowableCollector","methodName":"executeAndThrow","fileName":"RethrowingThrowableCollector.java","lineNumber":23},{"declaringClass":"io.cucumber.core.runtime.CucumberExecutionContext","methodName":"runTestCase","fileName":"CucumberExecutionContext.java","lineNumber":130},{"declaringClass":"io.cucumber.junit.FeatureRunner","methodName":"runChild","fileName":"FeatureRunner.java","lineNumber":144},{"declaringClass":"io.cucumber.junit.FeatureRunner","methodName":"runChild","fileName":"FeatureRunner.java","lineNumber":28},{"declaringClass":"io.cucumber.junit.FeatureRunner","methodName":"run","fileName":"FeatureRunner.java","lineNumber":137},{"declaringClass":"io.cucumber.junit.CucumberSerenityRunner","methodName":"runChild","fileName":"CucumberSerenityRunner.java","lineNumber":259},{"declaringClass":"io.cucumber.junit.CucumberSerenityRunner","methodName":"runChild","fileName":"CucumberSerenityRunner.java","lineNumber":59}]},"result":"FAILURE","precondition":false,"level":1}]}],"userStory":{"id":"as-a-user-i-want-to-get-user-information","storyName":"As a user i want to get user information","displayName":"As a user i want to get user information","path":"Auth/UserInfo.feature","type":"feature","qualifiedTag":{"name":"Auth/As a user i want to get user information","type":"feature","displayName":"Auth/As a user i want to get user information"}},"featureTag":{"name":"Auth/As a user i want to get user information","type":"feature","displayName":"Auth/As a user i want to get user information"},"title":"as user i want to input all valid data in get user information","description":"","tags":[{"name":"Auth/As a user i want to get user information","type":"feature","displayName":"As a user i want to get user information"},{"name":"Auth","type":"capability","displayName":"Auth"},{"name":"UserInfo","type":"tag","displayName":"UserInfo"}],"allTags":[{"name":"Auth/As a user i want to get user information","type":"feature","displayName":"As a user i want to get user information"},{"name":"Auth","type":"capability","displayName":"Auth"},{"name":"UserInfo","type":"tag","displayName":"UserInfo"}],"startTime":"2023-05-11T18:53:20.723+07:00[Asia/Bangkok]","duration":65718,"testFailureCause":{"errorType":"java.lang.AssertionError","message":"1 expectation failed.\nExpected status code \u003c200\u003e but was \u003c401\u003e.\n","stackTrace":[{"declaringClass":"io.restassured.internal.ResponseSpecificationImpl","methodName":"validateResponseIfRequired","fileName":"ResponseSpecificationImpl.groovy","lineNumber":696},{"declaringClass":"io.restassured.internal.ResponseSpecificationImpl","methodName":"this$2$validateResponseIfRequired","fileName":"ResponseSpecificationImpl.groovy","lineNumber":-1},{"declaringClass":"io.restassured.internal.ResponseSpecificationImpl","methodName":"statusCode","fileName":"ResponseSpecificationImpl.groovy","lineNumber":135},{"declaringClass":"io.restassured.internal.ResponseSpecificationImpl","methodName":"statusCode","fileName":"ResponseSpecificationImpl.groovy","lineNumber":143},{"declaringClass":"io.restassured.internal.ValidatableResponseOptionsImpl","methodName":"statusCode","fileName":"ValidatableResponseOptionsImpl.java","lineNumber":89},{"declaringClass":"starter.pages.UserInfoPage","methodName":"lambda$responseCode$0","fileName":"UserInfoPage.java","lineNumber":49},{"declaringClass":"net.serenitybdd.rest.SerenityRest","methodName":"restAssuredThat","fileName":"SerenityRest.java","lineNumber":626},{"declaringClass":"starter.pages.UserInfoPage","methodName":"responseCode","fileName":"UserInfoPage.java","lineNumber":49},{"declaringClass":"starter.stepdefinitions.UserInfoSteps","methodName":"userGetUserInformationStatusCode","fileName":"UserInfoSteps.java","lineNumber":37},{"declaringClass":"io.cucumber.java.Invoker","methodName":"doInvoke","fileName":"Invoker.java","lineNumber":66},{"declaringClass":"io.cucumber.java.Invoker","methodName":"invoke","fileName":"Invoker.java","lineNumber":24},{"declaringClass":"io.cucumber.java.AbstractGlueDefinition","methodName":"invokeMethod","fileName":"AbstractGlueDefinition.java","lineNumber":47},{"declaringClass":"io.cucumber.java.JavaStepDefinition","methodName":"execute","fileName":"JavaStepDefinition.java","lineNumber":29},{"declaringClass":"io.cucumber.core.runner.CoreStepDefinition","methodName":"execute","fileName":"CoreStepDefinition.java","lineNumber":66},{"declaringClass":"io.cucumber.core.runner.PickleStepDefinitionMatch","methodName":"runStep","fileName":"PickleStepDefinitionMatch.java","lineNumber":63},{"declaringClass":"io.cucumber.core.runner.TestStep","methodName":"executeStep","fileName":"TestStep.java","lineNumber":84},{"declaringClass":"io.cucumber.core.runner.TestStep","methodName":"run","fileName":"TestStep.java","lineNumber":56},{"declaringClass":"io.cucumber.core.runner.PickleStepTestStep","methodName":"run","fileName":"PickleStepTestStep.java","lineNumber":51},{"declaringClass":"io.cucumber.core.runner.TestCase","methodName":"run","fileName":"TestCase.java","lineNumber":84},{"declaringClass":"io.cucumber.core.runner.Runner","methodName":"runPickle","fileName":"Runner.java","lineNumber":75},{"declaringClass":"io.cucumber.core.runtime.CucumberExecutionContext","methodName":"lambda$runTestCase$5","fileName":"CucumberExecutionContext.java","lineNumber":130},{"declaringClass":"io.cucumber.core.runtime.RethrowingThrowableCollector","methodName":"executeAndThrow","fileName":"RethrowingThrowableCollector.java","lineNumber":23},{"declaringClass":"io.cucumber.core.runtime.CucumberExecutionContext","methodName":"runTestCase","fileName":"CucumberExecutionContext.java","lineNumber":130},{"declaringClass":"io.cucumber.junit.FeatureRunner","methodName":"runChild","fileName":"FeatureRunner.java","lineNumber":144},{"declaringClass":"io.cucumber.junit.FeatureRunner","methodName":"runChild","fileName":"FeatureRunner.java","lineNumber":28},{"declaringClass":"io.cucumber.junit.FeatureRunner","methodName":"run","fileName":"FeatureRunner.java","lineNumber":137},{"declaringClass":"io.cucumber.junit.CucumberSerenityRunner","methodName":"runChild","fileName":"CucumberSerenityRunner.java","lineNumber":259},{"declaringClass":"io.cucumber.junit.CucumberSerenityRunner","methodName":"runChild","fileName":"CucumberSerenityRunner.java","lineNumber":59}]},"testFailureClassname":"java.lang.AssertionError","testFailureMessage":"1 expectation failed.\nExpected status code \u003c200\u003e but was \u003c401\u003e.\n","testFailureSummary":"FAILURE;java.lang.AssertionError;1 expectation failed.\nExpected status code \u003c200\u003e but was \u003c401\u003e.\n;ResponseSpecificationImpl.groovy","projectKey":"","annotatedResult":"FAILURE","isManualTestingUpToDate":false,"context":"windows","manual":false,"testSource":"Cucumber","result":"FAILURE"}